[
    {"id": "acura", "img": ["./img_build_price/img0_1.jpg", "./img_build_price/img0_2.jpg", "./img_build_price/img0_3.jpg", "./img_build_price/img0_4.jpg", "./img_build_price/img0_5.jpg"], "name":["Integra", "MAX", "NSX", "RDX", "TLX"], "price": ["$32,695", "$51,045", "$171,495", "$42,945","$41,245"]},
    {"id": "alfa", "img": ["./img_build_price/img1_1.jpg", "./img_build_price/img1_2.jpg", "./img_build_price/img1_3.jpg","./img_build_price/img1_1.jpg"], "name":["Giulia", "Stelvio", "Tonale", "Atlas Cross Sport"], "price": ["$45,875", "$48,170","$44,590","$44,590"]},
    {"id": "audi", "img": ["./img_build_price/img2_1.jpg", "./img_build_price/img2_2.jpg", "./img_build_price/img2_3.jpg","./img_build_price/img2_4.jpg", "./img_build_price/img2_5.jpg", "./img_build_price/img2_6.jpg"], "name":["A3", "A4", "A5", "A6", "A7", "A8"], "price": ["$45,875", "$48,170","$44,590", "$45,875", "$48,170","$44,590"]},
    {"id": "bmw", "img": ["./img_build_price/img3_1.jpg", "./img_build_price/img3_2.jpg", "./img_build_price/img3_3.jpg","./img_build_price/img3_4.jpg", "./img_build_price/img3_5.jpg", "./img_build_price/img3_6.jpg"], "name":["X4", "X4M", "X5", "X7", "XM", "Z4"], "price": ["$45,875", "$48,170","$44,590", "$45,875", "$48,170","$44,590"]},
    {"id": "cadillac", "img": ["./img_build_price/img4_1.jpg", "./img_build_price/img4_2.jpg", "./img_build_price/img4_3.jpg","./img_build_price/img4_4.jpg"], "name":["CT4", "CT5", "CT5-V", "XT4"], "price": [ "$48,170","$44,590", "$45,875", "$48,170"]},
    {"id": "ford", "img": ["./img_build_price/img5_1.jpg", "./img_build_price/img5_2.jpg", "./img_build_price/img5_3.jpg","./img_build_price/img5_4.jpg","./img_build_price/img5_5.jpg"], "name":["Bronco", "Bronco Sport", "EcoSport", "Edge", "Escape"], "price": [ "$48,170","$44,590", "$45,875", "$48,170", "$48,170"]},
    {"id": "gmc", "img": ["./img_build_price/img6_1.jpg", "./img_build_price/img6_2.jpg", "./img_build_price/img6_3.jpg","./img_build_price/img6_4.jpg","./img_build_price/img6_5.jpg"], "name":["Sierra 3500HD", "Sierra 2500HD", "Sierra 1500 Limited", "Terrain", "Yukon"], "price": [ "$48,170","$44,590", "$45,875", "$48,170", "$48,170"]},
    {"id": "honda", "img": ["./img_build_price/img7_1.jpg", "./img_build_price/img7_2.jpg", "./img_build_price/img7_3.jpg","./img_build_price/img7_4.jpg"], "name":["HR-V", "CR-V", "Civic","Pilot"], "price": [ "$48,170","$44,590", "$45,875", "$48,170", "$48,170"]},
    {"id": "hyundai", "img": ["./img_build_price/img6_1.jpg", "./img_build_price/img6_2.jpg", "./img_build_price/img6_3.jpg","./img_build_price/img6_4.jpg","./img_build_price/img6_5.jpg"], "name":["Elantra", "IONIQ 6", "Palisade", "Sonata", "Venue"], "price": [ "$48,170","$44,590", "$45,875", "$48,170", "$48,170"]},
    {"id": "land-Rover", "img": ["./img_build_price/img2_1.jpg", "./img_build_price/img2_2.jpg", "./img_build_price/img2_3.jpg","./img_build_price/img2_4.jpg", "./img_build_price/img2_5.jpg", "./img_build_price/img2_6.jpg"], "name":["Range Rover Sport", "Range Rover Velar", "Discovery Sport", "Defender", "Range Rover", "Range Rover Evoque"], "price": ["$45,875", "$48,170","$44,590", "$45,875", "$48,170","$44,590"]},
    {"id": "lexus", "img": ["./img_build_price/img5_1.jpg", "./img_build_price/img5_2.jpg", "./img_build_price/img5_3.jpg","./img_build_price/img5_4.jpg","./img_build_price/img5_5.jpg"], "name":["ES", "GX", "IS", "LC", "LS"], "price": [ "$48,170","$44,590", "$45,875", "$48,170", "$48,170"]},
    {"id": "maserati", "img": ["./img_build_price/img0_1.jpg", "./img_build_price/img0_2.jpg", "./img_build_price/img0_3.jpg", "./img_build_price/img0_4.jpg", "./img_build_price/img0_5.jpg"], "name":["Levante", "MC20", "Quattroporte", "Ghibli", "Grecale"], "price": ["$32,695", "$51,045", "$171,495", "$42,945","$41,245"]},
    {"id": "mazda", "img": ["./img_build_price/img1_1.jpg", "./img_build_price/img1_2.jpg", "./img_build_price/img1_3.jpg","./img_build_price/img1_1.jpg"], "name":["CX30", "CX4", "CX5", "CX-50"], "price": ["$45,875", "$48,170","$44,590","$44,590"]},
    {"id": "mercedes-benz", "img": ["./img_build_price/img6_1.jpg", "./img_build_price/img6_2.jpg", "./img_build_price/img6_3.jpg","./img_build_price/img6_4.jpg","./img_build_price/img6_5.jpg"], "name":["AMG LT", "CLS", "CLA", "EQB", "GLC"], "price": [ "$48,170","$44,590", "$45,875", "$48,170", "$48,170"]},
    {"id": "mini", "img": ["./img_build_price/img6_1.jpg", "./img_build_price/img6_2.jpg", "./img_build_price/img6_3.jpg","./img_build_price/img6_4.jpg","./img_build_price/img6_5.jpg"], "name":["Hardtop", "Electric Hardtop", "Clubman", "Convertible", "Countryman"], "price": [ "$48,170","$44,590", "$45,875", "$48,170", "$48,170"]},
    {"id": "mitsubishi", "img": ["./img_build_price/img4_1.jpg", "./img_build_price/img4_2.jpg", "./img_build_price/img4_3.jpg","./img_build_price/img4_4.jpg"], "name":["Eclipse Cross", "Mirage", "Outlander", "Outlander Sport"], "price": [ "$48,170","$44,590", "$45,875", "$48,170"]},
    {"id": "porsche", "img": ["./img_build_price/img6_1.jpg", "./img_build_price/img6_2.jpg", "./img_build_price/img6_3.jpg","./img_build_price/img6_4.jpg","./img_build_price/img6_5.jpg"], "name":["718 Boxster", "718 Cayman", "911", "Cayenne", "Taycan"], "price": [ "$48,170","$44,590", "$45,875", "$48,170", "$48,170"]},
    {"id": "toyota", "img": ["./img_build_price/img0_1.jpg", "./img_build_price/img0_2.jpg", "./img_build_price/img0_3.jpg", "./img_build_price/img0_4.jpg", "./img_build_price/img0_5.jpg"], "name":["Camry", "Corolla Cross", "GR86", "GR Supra", "Prius Prime"], "price": ["$32,695", "$51,045", "$171,495", "$42,945","$41,245"]}
]
